b_hunters-1.1.16-nspkg.pth
b_hunters/__version__.py
b_hunters/bhunter.py
b_hunters/cli.py
b_hunters/main.py
b_hunters-1.1.16.dist-info/METADATA
b_hunters-1.1.16.dist-info/WHEEL
b_hunters-1.1.16.dist-info/entry_points.txt
b_hunters-1.1.16.dist-info/namespace_packages.txt
b_hunters-1.1.16.dist-info/top_level.txt
b_hunters-1.1.16.dist-info/RECORD
