Metadata-Version: 2.1
Name: b-hunters
Version: 1.1.16
Summary: **B-Hunters** is a bug bounty framework built on the Karton
Home-page: https://github.com/B-Hunters/B-Hunters
License: UNKNOWN
Platform: UNKNOWN
Classifier: Programming Language :: Python :: 3
Classifier: Operating System :: OS Independent
Classifier: License :: OSI Approved :: BSD License
Requires-Python: >=3.8
Requires-Dist: colorama
Requires-Dist: karton-core (==5.5.0)
Requires-Dist: pymongo
Requires-Dist: requests
Requires-Dist: tldextract
